snipara_mcp/__init__.py
snipara_mcp/auth.py
snipara_mcp/py.typed
snipara_mcp/rlm_tools.py
snipara_mcp/server.py
snipara_mcp-2.3.0.dist-info/METADATA
snipara_mcp-2.3.0.dist-info/WHEEL
snipara_mcp-2.3.0.dist-info/entry_points.txt
snipara_mcp-2.3.0.dist-info/licenses/LICENSE
snipara_mcp-2.3.0.dist-info/RECORD
