Metadata-Version: 2.3
Name: snipara-mcp
Version: 2.3.0
Summary: MCP server for Snipara - Context optimization and Agent infrastructure for LLMs
Project-URL: Homepage, https://snipara.com
Project-URL: Documentation, https://docs.snipara.com
Project-URL: Repository, https://github.com/Snipara/snipara-server
Author-email: Snipara <support@snipara.com>
License: MIT
License-File: LICENSE
Keywords: agents,claude,context,cursor,documentation,llm,mcp,memory,multi-agent,rlm,snipara,swarm
Classifier: Development Status :: 4 - Beta
Classifier: Intended Audience :: Developers
Classifier: License :: OSI Approved :: MIT License
Classifier: Programming Language :: Python :: 3
Classifier: Programming Language :: Python :: 3.10
Classifier: Programming Language :: Python :: 3.11
Classifier: Programming Language :: Python :: 3.12
Requires-Python: >=3.10
Requires-Dist: httpx>=0.26.0
Requires-Dist: mcp>=1.25.0
Provides-Extra: rlm
Requires-Dist: rlm-runtime>=0.1.0; extra == 'rlm'
